gpgram/__init__.py
gpgram/bot.py
gpgram/dispatcher.py
gpgram/logging.py
gpgram/py.typed
gpgram/router.py
gpgram/webhook.py
gpgram/common/__init__.py
gpgram/common/bot.py
gpgram/common/button.py
gpgram/common/handler.py
gpgram/common/message.py
gpgram/filters/__init__.py
gpgram/filters/base.py
gpgram/filters/message_filters.py
gpgram/handlers/__init__.py
gpgram/handlers/base.py
gpgram/handlers/callback_query_handler.py
gpgram/handlers/inline_query_handler.py
gpgram/handlers/message_handler.py
gpgram/middleware/__init__.py
gpgram/middleware/base.py
gpgram/middleware/rate_limit.py
gpgram/types/__init__.py
gpgram/types/base.py
gpgram/types/callback_query.py
gpgram/types/chat.py
gpgram/types/message.py
gpgram/types/update.py
gpgram/types/user.py
gpgram/utils/__init__.py
gpgram/utils/conversation.py
gpgram/utils/helpers.py
gpgram/utils/keyboard.py
gpgram/utils/media.py
gpgram-0.2.0.dist-info/licenses/LICENSE
gpgram-0.2.0.dist-info/METADATA
gpgram-0.2.0.dist-info/WHEEL
gpgram-0.2.0.dist-info/top_level.txt
gpgram-0.2.0.dist-info/RECORD
