Metadata-Version: 2.4
Name: gpgram
Version: 0.2.0
Summary: A modern, asynchronous Telegram Bot API library with advanced handler capabilities
Home-page: https://github.com/GrandpaEJ/gpgram
Author: Gpgram Team
Author-email: 
License: MIT
Project-URL: Documentation, https://gpgram.readthedocs.io/
Project-URL: Source, https://github.com/GrandpaEJ/gpgram
Project-URL: Tracker, https://github.com/GrandpaEJ/gpgram/issues
Keywords: telegram,bot,api,async,asyncio,python,webhook,conversation,inline,keyboard,middleware
Classifier: Programming Language :: Python :: 3
Classifier: Programming Language :: Python :: 3.8
Classifier: Programming Language :: Python :: 3.9
Classifier: Programming Language :: Python :: 3.10
Classifier: Programming Language :: Python :: 3.11
Classifier: Operating System :: OS Independent
Classifier: Topic :: Communications :: Chat
Classifier: Topic :: Software Development :: Libraries :: Python Modules
Classifier: Framework :: AsyncIO
Requires-Python: >=3.8
License-File: LICENSE
Requires-Dist: httpx>=0.23.0
Requires-Dist: pydantic>=1.9.0
Requires-Dist: typing-extensions>=4.0.0
Requires-Dist: loguru>=0.7.0
Requires-Dist: aiohttp>=3.8.0
Requires-Dist: python-multipart>=0.0.5
Provides-Extra: dev
Requires-Dist: pytest>=7.0.0; extra == "dev"
Requires-Dist: pytest-asyncio>=0.18.0; extra == "dev"
Requires-Dist: black>=22.1.0; extra == "dev"
Requires-Dist: isort>=5.10.0; extra == "dev"
Requires-Dist: mypy>=0.931; extra == "dev"
Requires-Dist: twine>=4.0.0; extra == "dev"
Requires-Dist: build>=0.10.0; extra == "dev"
Provides-Extra: docs
Requires-Dist: sphinx>=4.0.0; extra == "docs"
Requires-Dist: sphinx-rtd-theme>=1.0.0; extra == "docs"
Requires-Dist: myst-parser>=0.15.0; extra == "docs"
Requires-Dist: sphinx-copybutton>=0.5.0; extra == "docs"
Requires-Dist: sphinx-autodoc-typehints>=1.12.0; extra == "docs"
Provides-Extra: webhook
Requires-Dist: aiohttp>=3.8.0; extra == "webhook"
Dynamic: author
Dynamic: classifier
Dynamic: description
Dynamic: description-content-type
Dynamic: home-page
Dynamic: keywords
Dynamic: license
Dynamic: license-file
Dynamic: project-url
Dynamic: provides-extra
Dynamic: requires-dist
Dynamic: requires-python
Dynamic: summary
